MANIFEST.in
README
setup.py
django_kungfu/__init__.py
django_kungfu/configurator.py
django_kungfu.egg-info/PKG-INFO
django_kungfu.egg-info/SOURCES.txt
django_kungfu.egg-info/dependency_links.txt
django_kungfu.egg-info/pbr.json
django_kungfu.egg-info/top_level.txt