Metadata-Version: 1.1
Name: django-kungfu
Version: 0.2
Summary: A Flasky approach to distributed Django configuration
Home-page: https://github.com/delinhabit/django-kungfu
Author: Ion Scerbatiuc
Author-email: delinhabit@gmail.com
License: BSD
Keywords: django settings overrides flasky
Platform: UNKNOWN
Classifier: Development Status :: 5 - Production/Stable
Classifier: Framework :: Django
Classifier: Intended Audience :: Developers
Classifier: License :: OSI Approved :: BSD License
Classifier: Operating System :: OS Independent
Classifier: Programming Language :: Python
Classifier: Topic :: Software Development
Classifier: Topic :: Software Development :: Libraries :: Application Frameworks
